sphericart/__init__.py
sphericart/_c_lib.py
sphericart/metatensor.py
sphericart/spherical_harmonics.py
sphericart/include/cuda_base.hpp
sphericart/include/cuda_cache.hpp
sphericart/include/dynamic_cuda.hpp
sphericart/include/macros.hpp
sphericart/include/sphericart.h
sphericart/include/sphericart.hpp
sphericart/include/sphericart_cuda.hpp
sphericart/include/sphericart_impl.cuh
sphericart/include/templates.hpp
sphericart/include/templates_core.hpp
sphericart/include/sphericart/exports.h
sphericart/lib/libsphericart.so
sphericart/lib/cmake/sphericart/sphericart-config-version.cmake
sphericart/lib/cmake/sphericart/sphericart-config.cmake
sphericart/lib/cmake/sphericart/sphericart-targets-release.cmake
sphericart/lib/cmake/sphericart/sphericart-targets.cmake
sphericart.libs/libgomp-e985bcbb.so.1.0.0
sphericart-1.0.5.dist-info/METADATA
sphericart-1.0.5.dist-info/WHEEL
sphericart-1.0.5.dist-info/top_level.txt
sphericart-1.0.5.dist-info/RECORD
sphericart-1.0.5.dist-info/licenses/LICENSE-APACHE
sphericart-1.0.5.dist-info/licenses/LICENSE-MIT
sphericart-1.0.5.dist-info/licenses/LICENSE.md
sphericart-1.0.5.dist-info/sboms/auditwheel.cdx.json
