Metadata-Version: 2.4
Name: sphericart
Version: 1.0.5
Summary: Fast calculation of spherical harmonics
Author: Filippo Bigi, Guillaume Fraux, Nicholas Browning, Michele Ceriotti
License-Expression: Apache-2.0 OR MIT
Project-URL: homepage, https://github.com/lab-cosmo/sphericart
Project-URL: documentation, https://sphericart.readthedocs.io/en/latest/
Project-URL: repository, https://github.com/lab-cosmo/sphericart
Keywords: spherical harmonics
Classifier: Development Status :: 4 - Beta
Classifier: Intended Audience :: Science/Research
Classifier: Operating System :: POSIX
Classifier: Operating System :: MacOS :: MacOS X
Classifier: Programming Language :: Python
Classifier: Programming Language :: Python :: 3
Classifier: Topic :: Scientific/Engineering
Classifier: Topic :: Scientific/Engineering :: Physics
Classifier: Topic :: Software Development :: Libraries
Classifier: Topic :: Software Development :: Libraries :: Python Modules
Requires-Python: >=3.9
License-File: LICENSE-APACHE
License-File: LICENSE-MIT
License-File: LICENSE.md
Requires-Dist: numpy
Provides-Extra: torch
Requires-Dist: sphericart-torch; extra == "torch"
Provides-Extra: jax
Requires-Dist: sphericart-jax; extra == "jax"
Dynamic: license-file
Dynamic: provides-extra
